<annotation>
	<folder>train</folder>
	<filename>znak075.JPG</filename>
	<path>C:\Users\Barbara\Desktop\fer\6.sem\zavrsni\Tensorflow\data\train\znak075.JPG</path>
	<source>
		<database>Unknown</database>
	</source>
	<size>
		<width>828</width>
		<height>1157</height>
		<depth>3</depth>
	</size>
	<segmented>0</segmented>
	<object>
		<name>DivljaÄ na cesti</name>
		<pose>Unspecified</pose>
		<truncated>0</truncated>
		<difficult>0</difficult>
		<bndbox>
			<xmin>509</xmin>
			<ymin>678</ymin>
			<xmax>623</xmax>
			<ymax>780</ymax>
		</bndbox>
	</object>
</annotation>
